CHANGES.rst
CONTRIBUTORS.rst
MANIFEST.in
README.rst
VERSION
VERSION_SUFFIX
setup.cfg
setup.py
test.rst
docs/LICENSE.GPL
docs/LICENSE.rst
docs/index.rst
src/visaplan/__init__.py
src/visaplan.plone.behaviors.egg-info/PKG-INFO
src/visaplan.plone.behaviors.egg-info/SOURCES.txt
src/visaplan.plone.behaviors.egg-info/dependency_links.txt
src/visaplan.plone.behaviors.egg-info/entry_points.txt
src/visaplan.plone.behaviors.egg-info/namespace_packages.txt
src/visaplan.plone.behaviors.egg-info/not-zip-safe
src/visaplan.plone.behaviors.egg-info/requires.txt
src/visaplan.plone.behaviors.egg-info/top_level.txt
src/visaplan/plone/__init__.py
src/visaplan/plone/behaviors/__init__.py
src/visaplan/plone/behaviors/behaviors.zcml
src/visaplan/plone/behaviors/configure.zcml
src/visaplan/plone/behaviors/factories.py
src/visaplan/plone/behaviors/interfaces.py
src/visaplan/plone/behaviors/setuphandlers.py
src/visaplan/plone/behaviors/testing.py
src/visaplan/plone/behaviors/locales/visaplan.plone.behaviors.pot
src/visaplan/plone/behaviors/locales/de/LC_MESSAGES/visaplan.plone.behaviors.mo
src/visaplan/plone/behaviors/locales/de/LC_MESSAGES/visaplan.plone.behaviors.po
src/visaplan/plone/behaviors/profiles/default/browserlayer.xml
src/visaplan/plone/behaviors/profiles/default/catalog.xml
src/visaplan/plone/behaviors/profiles/default/metadata.xml
src/visaplan/plone/behaviors/profiles/default/registry.xml
src/visaplan/plone/behaviors/profiles/uninstall/browserlayer.xml
src/visaplan/plone/behaviors/tests/__init__.py
src/visaplan/plone/behaviors/tests/test_ct_folderish_animation.py
src/visaplan/plone/behaviors/tests/test_robot.py
src/visaplan/plone/behaviors/tests/test_setup.py
src/visaplan/plone/behaviors/tests/robot/test_example.robot