Metadata-Version: 2.1
Name: visaplan.plone.behaviors
Version: 1.0.2.post2
Summary: Interfaces and behaviors for a family of Plone/Dexterity datatypes
Home-page: UNKNOWN
Author: Tobias Herp
Author-email: tobias.herp@visaplan.com
License: GPL version 2
Project-URL: Source, https://github.com/visaplan/plone.behaviors
Project-URL: Documentation, https://pypi.org/project/visaplan.plone.behaviors
Project-URL: Tracker, https://github.com/visaplan/plone.behaviors/issues
Platform: UNKNOWN
Classifier: Environment :: Web Environment
Classifier: Framework :: Plone
Classifier: Framework :: Plone :: 4.3
Classifier: Framework :: Zope2
Classifier: Programming Language :: Python
Classifier: Programming Language :: Python :: 2.7
Classifier: Intended Audience :: Developers
Classifier: Natural Language :: German
Classifier: Operating System :: OS Independent
Classifier: License :: OSI Approved :: GNU General Public License v2 (GPLv2)
Provides-Extra: test
